story_1/__init__.py
story_1/module.MD
story_1/module.s.HTML
story_1/names.s.HTML
"story_1/""agenda v1""/core values.r.html"
"story_1/""agenda v1""/governance.r.html"
"story_1/""agenda v1""/priorities.html"
"story_1/""agenda v2""/priorities.s.HTML"
"story_1/""agenda""/agenda, seed.s.HTML"
"story_1/""agenda""/agenda, vibes.s.HTML"
"story_1/""agenda""/agenda.s.HTML"
"story_1/""agenda""/databases/databases.s.HTML"
"story_1/""agenda""/databases/merchants/merchants.s.HTML"
"story_1/""agenda""/databases/moves/moves.s.HTML"
"story_1/""agenda""/keys/keys.s.HTML"
"story_1/""agenda""/voting/voting.s.HTML"
"story_1/""agenda""/voting/bouncer/bouncer.s.HTML"
story_1/__book/codesweeper--ai-generated-8311435_1920.jpg
story_1/__license/license.s.HTML
story_1/__license/options/gpl-3.0-standalone.html
story_1/_clique/__init__.py
story_1/_clique/group/__init__.py
story_1/_status/__init__.py
story_1/_status/status.proc.py
story_1/belt/__init__.py
story_1/belt/module.s.HTML
story_1/belt/names.s.HTML
story_1/belt/start.proc.py
story_1/belt/__agenda/agenda.s.HTML
story_1/belt/__book/TheDigitalArtist--ai-generated-8228359_1920.jpg
story_1/belt/__book/TheDigitalArtist--ai-generated-8228360_1920.jpg
story_1/belt/__book/dlsdkcgl--hidden-8315722_1920.jpg
story_1/belt/__book/_hardware/hardware.s.HTML
story_1/belt/__book/_hardware/ISO/ISO_lab.s.HTML
story_1/belt/__book/_hardware/ISO/ISO_lab_2.s.HTML
story_1/belt/__book/_hardware/ISO/write_ISO_to_drive.py
story_1/belt/__book/_hardware/docker/docker.s.HTML
story_1/belt/__book/_hardware/docker/essential_installations.s.HTML
story_1/belt/__book/_hardware/docker/compose/compose.s.HTML
story_1/belt/__book/_hardware/docker/containers/containers.s.HTML
story_1/belt/__book/_hardware/docker/containers/installations.s.HTML
story_1/belt/__book/_hardware/docker/images/images.s.HTML
story_1/belt/_status/status_1.py
story_1/belt/awareness/clique/__init__.py
story_1/belt/awareness/sockets/__init__.py
story_1/belt/awareness/sockets/clique_group.py
story_1-2.0.3.dist-info/METADATA
story_1-2.0.3.dist-info/WHEEL
story_1-2.0.3.dist-info/entry_points.txt
story_1-2.0.3.dist-info/top_level.txt
story_1-2.0.3.dist-info/RECORD
