Metadata-Version: 2.1
Name: story_1
Version: 2.0.3
Summary: The dreams that found there way to a canvas.
License: GPL 3.0 + MongoDB SSPL
Requires-Dist: bracelet
Requires-Dist: carbonado
Requires-Dist: ships
Requires-Dist: asn1crypto
Requires-Dist: click
Requires-Dist: ecdsa
Requires-Dist: ECPy
Requires-Dist: flask
Requires-Dist: rich
Requires-Dist: selenium
Requires-Dist: textual
Requires-Dist: websockets
Requires-Dist: pycryptodome
Requires-Dist: PyOpenSSL
Requires-Dist: pymongo
Requires-Dist: qrcode
